MCDBuild/FoundPos.py
MCDBuild/MCDDownload.py
MCDBuild/__init__.py
MCDBuild/create.py
MCDBuild/verification_hdf.py
MCD15Viwer-1.0.dist-info/LICENSE
MCD15Viwer-1.0.dist-info/METADATA
MCD15Viwer-1.0.dist-info/WHEEL
MCD15Viwer-1.0.dist-info/top_level.txt
MCD15Viwer-1.0.dist-info/RECORD
