Metadata-Version: 2.1
Name: MCD15Viwer
Version: 1.0
Summary: help download modis files with token and muti threading processing
Home-page: https://github.com/qxcnwu
Author: qxcnwu
Author-email: qxcnwu@gmail.com
Maintainer: qxcnwu
Maintainer-email: qxcnwu@gmail.com
License: MIT License
Platform: UNKNOWN
Classifier: Development Status :: 3 - Alpha
Classifier: Intended Audience :: Developers
Classifier: Topic :: Software Development :: Build Tools
Classifier: License :: OSI Approved :: MIT License
Classifier: Programming Language :: Python :: 3
Requires-Python: >=3.4
Requires-Dist: tqdm
Requires-Dist: numpy
Requires-Dist: pandas
Requires-Dist: h5py
Requires-Dist: ModisDownload
